dqsegdb2/__init__.py
dqsegdb2/_version.py
dqsegdb2/api.py
dqsegdb2/query.py
dqsegdb2/requests.py
dqsegdb2/utils.py
dqsegdb2/tests/__init__.py
dqsegdb2/tests/test_api.py
dqsegdb2/tests/test_query.py
dqsegdb2-1.2.1.dist-info/LICENSE
dqsegdb2-1.2.1.dist-info/METADATA
dqsegdb2-1.2.1.dist-info/WHEEL
dqsegdb2-1.2.1.dist-info/top_level.txt
dqsegdb2-1.2.1.dist-info/RECORD
