Metadata-Version: 2.1
Name: dqsegdb2
Version: 1.2.1
Summary: Simplified python interface to DQSEGDB
Home-page: https://pypi.org/project/dqsegdb2/
Author: Duncan Macleod
Author-email: duncan.macleod@ligo.org
License: GPL-3.0-or-later
Project-URL: Bug Tracker, https://git.ligo.org/duncanmmacleod/dqsegdb2/-/issues
Project-URL: Documentation, https://dqsegdb2.readthedocs.io
Project-URL: Source Code, https://git.ligo.org/duncanmmacleod/dqsegdb2.git
Classifier: Development Status :: 4 - Beta
Classifier: Intended Audience :: Science/Research
Classifier: Intended Audience :: End Users/Desktop
Classifier: Intended Audience :: Developers
Classifier: License :: OSI Approved :: GNU General Public License v3 or later (GPLv3+)
Classifier: Natural Language :: English
Classifier: Operating System :: OS Independent
Classifier: Programming Language :: Python
Classifier: Programming Language :: Python :: 3
Classifier: Programming Language :: Python :: 3.6
Classifier: Programming Language :: Python :: 3.7
Classifier: Programming Language :: Python :: 3.8
Classifier: Programming Language :: Python :: 3.9
Classifier: Programming Language :: Python :: 3.10
Classifier: Programming Language :: Python :: 3.11
Classifier: Topic :: Scientific/Engineering
Classifier: Topic :: Scientific/Engineering :: Astronomy
Classifier: Topic :: Scientific/Engineering :: Physics
Requires-Python: >=3.6
License-File: LICENSE
Requires-Dist: igwn-auth-utils >=1.0.0
Requires-Dist: ligo-segments >=1.0.0
Provides-Extra: docs
Requires-Dist: sphinx ; extra == 'docs'
Requires-Dist: sphinx-automodapi ; extra == 'docs'
Requires-Dist: sphinx-rtd-theme ; extra == 'docs'
Provides-Extra: lint
Requires-Dist: flake8 >=3.7.0 ; extra == 'lint'
Requires-Dist: flake8-bandit ; extra == 'lint'
Provides-Extra: test
Requires-Dist: pytest >=2.9.2 ; extra == 'test'
Requires-Dist: pytest-cov >=2.5.1 ; extra == 'test'
Requires-Dist: requests-mock >=1.5.0 ; extra == 'test'
